cursesUI/__init__.py
cursesUI/base.py
cursesUI/constants.py
cursesUI/ui.py
logic/__init__.py
logic/game.py
tictactoe_marlene-0.1.5.dist-info/WHEEL
tictactoe_marlene-0.1.5.dist-info/METADATA
tictactoe_marlene-0.1.5.dist-info/RECORD
