Metadata-Version: 2.1
Name: tictactoe-marlene
Version: 0.1.5
Summary: Tic Tac Toe game made with Python and Curses
Author: Marlene Nunes
Requires-Python: >=3.8.10,<4.0.0
Classifier: Programming Language :: Python :: 3
Classifier: Programming Language :: Python :: 3.10
Classifier: Programming Language :: Python :: 3.9
Requires-Dist: certifi (==2021.10.8)
Requires-Dist: pip (==21.2.4)
Requires-Dist: setuptools (==58.0.4)
Requires-Dist: wheel (==0.37.0)
